gcptool/__init__.py
gcptool/__main__.py
gcptool/creds.py
gcptool/findings/base.md
gcptool/findings/cloudfunctions_triggerable.md
gcptool/findings/compute_allspotter.md
gcptool/findings/compute_firewall_all_ports.md
gcptool/findings/compute_firewall_internal.md
gcptool/findings/compute_firewall_public.md
gcptool/findings/compute_firewall_rdp.md
gcptool/findings/compute_firewall_ssh.md
gcptool/findings/compute_http.md
gcptool/findings/compute_tlsv1.md
gcptool/findings/finding_template.md
gcptool/findings/gcs_bucket_logging.md
gcptool/findings/gcs_bucket_versioning.md
gcptool/findings/gcs_write_buckets.md
gcptool/findings/gke_hardening.md
gcptool/findings/gke_metadata.md
gcptool/findings/gke_public.md
gcptool/findings/iam_key_rotation.md
gcptool/findings/iam_primitive.md
gcptool/findings/iam_service_roles.md
gcptool/findings/iam_user_managed_keys.md
gcptool/findings/sql_tls.md
gcptool/inventory/__init__.py
gcptool/inventory/cache.py
gcptool/inventory/bigquery/__init__.py
gcptool/inventory/bigquery/api.py
gcptool/inventory/cloudfunctions/__init__.py
gcptool/inventory/cloudfunctions/api.py
gcptool/inventory/cloudfunctions/functions.py
gcptool/inventory/cloudfunctions/types.py
gcptool/inventory/compute/__init__.py
gcptool/inventory/compute/addresses.py
gcptool/inventory/compute/api.py
gcptool/inventory/compute/backend_buckets.py
gcptool/inventory/compute/backend_services.py
gcptool/inventory/compute/firewalls.py
gcptool/inventory/compute/forwarding_rules.py
gcptool/inventory/compute/instances.py
gcptool/inventory/compute/network_endpoint_groups.py
gcptool/inventory/compute/regions.py
gcptool/inventory/compute/ssl_certs.py
gcptool/inventory/compute/ssl_policies.py
gcptool/inventory/compute/target_http_proxies.py
gcptool/inventory/compute/target_https_proxies.py
gcptool/inventory/compute/target_ssl_proxies.py
gcptool/inventory/compute/target_tcp_proxies.py
gcptool/inventory/compute/types.py
gcptool/inventory/compute/vpn_gateways.py
gcptool/inventory/compute/zones.py
gcptool-1.1.1.dist-info/METADATA
gcptool-1.1.1.dist-info/WHEEL
gcptool-1.1.1.dist-info/entry_points.txt
gcptool-1.1.1.dist-info/RECORD
