Metadata-Version: 2.1
Name: gcptool
Version: 1.1.1
Project-URL: GitHub, https://github.com/CarveSystems/gcptool
Author-email: Aidan Noll <aidan.noll@carvesystems.com>
Requires-Python: >=3.8
Requires-Dist: google-api-python-client
Requires-Dist: google-cloud-container
Requires-Dist: google-cloud-resource-manager
Requires-Dist: google-cloud-storage
Requires-Dist: jinja2
Requires-Dist: netaddr
Requires-Dist: pydantic
